awyes/__init__.py
awyes/awyes.py
awyes/constants.py
awyes/deploy.py
awyes/utils.py
awyes-14.0.18.dist-info/METADATA
awyes-14.0.18.dist-info/WHEEL
awyes-14.0.18.dist-info/entry_points.txt
awyes-14.0.18.dist-info/top_level.txt
awyes-14.0.18.dist-info/RECORD
