Metadata-Version: 2.1
Name: awyes
Version: 14.0.18
Summary: A package for easy setup and management of resources on AWS
Home-page: https://github.com/bb-labs/awyes
Author: Truman Purnell
Author-email: truman.purnell@gmail.com
Keywords: aws resources manager setup management automation
Classifier: Development Status :: 3 - Alpha
Classifier: Intended Audience :: Developers
Classifier: License :: OSI Approved :: MIT License
Classifier: Programming Language :: Python :: 3
Classifier: Programming Language :: Python :: 3.6
Classifier: Programming Language :: Python :: 3.7
Classifier: Programming Language :: Python :: 3.8
Classifier: Programming Language :: Python :: 3.9
Requires-Dist: pyyaml
Requires-Dist: python-dotenv
Requires-Dist: pip
Requires-Dist: pipfile
Requires-Dist: rich
